jaxkineticmodel/__init__.py
jaxkineticmodel/utils.py
jaxkineticmodel/building_models/JaxKineticModelBuild.py
jaxkineticmodel/building_models/__init__.py
jaxkineticmodel/kinetic_mechanisms/JaxKineticMechanisms.py
jaxkineticmodel/kinetic_mechanisms/JaxKineticMechanismsCustom.py
jaxkineticmodel/kinetic_mechanisms/JaxKineticModifiers.py
jaxkineticmodel/kinetic_mechanisms/__init__.py
jaxkineticmodel/load_sbml/__init__.py
jaxkineticmodel/load_sbml/export_sbml.py
jaxkineticmodel/load_sbml/jax_kinetic_model.py
jaxkineticmodel/load_sbml/sbml_load_utils.py
jaxkineticmodel/load_sbml/sbml_model.py
jaxkineticmodel/load_sbml/sympy_converter.py
jaxkineticmodel/parameter_estimation/__init__.py
jaxkineticmodel/parameter_estimation/initialize_parameters.py
jaxkineticmodel/parameter_estimation/jacobian.py
jaxkineticmodel/parameter_estimation/training.py
jaxkineticmodel/simulated_dbtl/__init__.py
jaxkineticmodel/simulated_dbtl/dbtl.py
jaxkineticmodel-0.0.4.dist-info/LICENSE
jaxkineticmodel-0.0.4.dist-info/METADATA
jaxkineticmodel-0.0.4.dist-info/WHEEL
jaxkineticmodel-0.0.4.dist-info/top_level.txt
jaxkineticmodel-0.0.4.dist-info/RECORD
