Metadata-Version: 2.1
Name: jaxkineticmodel
Version: 0.0.4
Summary: A tool for building, training, and simulating metabolic kinetic models in Jax/Diffrax
Author-email: Paul van Lent <p.h.vanlent@tudelft.nl>, Léon Planken <l.r.planken@tudelft.nl>, Thomas Abeel <t.abeel@tudelft.nl>
Classifier: Programming Language :: Python :: 3
Classifier: License :: OSI Approved :: Apache Software License
Classifier: Operating System :: OS Independent
Requires-Python: >=3.9
License-File: LICENSE
Requires-Dist: diffrax >=0.6.0
Requires-Dist: equinox >=0.11.8
Requires-Dist: functions ==0.7.0
Requires-Dist: jax ==0.4.35
Requires-Dist: jaxlib ==0.4.35
Requires-Dist: matplotlib >=3.9.2
Requires-Dist: optax ==0.2.3
Requires-Dist: pandas >=1.1.4
Requires-Dist: pytest >=8.3.4
Requires-Dist: scikit-learn ==1.5.2
Requires-Dist: scipy >=1.11.1
Requires-Dist: sympy >=1.13.3
Requires-Dist: python-libsbml ==5.20.4
Requires-Dist: scikit-optimize >=0.10.2
Requires-Dist: markdown-include >=0.8.1
Requires-Dist: xgboost >=2.1.3
Requires-Dist: tomli >=2.1.0 ; python_version < "3.11"
Provides-Extra: test
Requires-Dist: libroadrunner >=2.7.0 ; extra == 'test'
